{
	"AttributesTolerance": 1,
	"IndentWithTabs": true,
	"KeepFirstAttributeOnSameLine": true,
	"MaxAttributeCharactersPerLine": 0,
	"MaxAttributesPerLine": 1,
	"NewlineExemptionElements": "RadialGradientBrush, GradientStop, LinearGradientBrush, ScaleTransform, SkewTransform, RotateTransform, TranslateTransform, Trigger, Condition, Setter, StaticResource",
	"SeparateByGroups": false,
	"AttributeIndentation": 0,
	"AttributeIndentationStyle": 0,
	"RemoveDesignTimeReferences":  false,
	"IgnoreDesignTimeReferencePrefix": false,
	"EnableAttributeReordering": false,
	"FirstLineAttributes": "",
	"OrderAttributesByName": false,
	"PutEndingBracketOnNewLine": false,
	"RemoveEndingTagOfEmptyElement": true,
	"SpaceBeforeClosingSlash": true,
	"RootElementLineBreakRule": 0,
	"ReorderVSM": 0,
	"ReorderGridChildren": false,
	"ReorderCanvasChildren": false,
	"ReorderSetters": 0,
	"FormatMarkupExtension": true,
	"NoNewLineMarkupExtensions": "x:Bind, Binding",
	"ThicknessSeparator": 2,
	"ThicknessAttributes": "Margin, Padding, BorderThickness, ThumbnailClipMargin",
	"FormatOnSave": false,
	"CommentPadding": 1
}